mixam_sdk/__init__.py
mixam_sdk/ai_bridge/__init__.py
mixam_sdk/ai_bridge/size.py
mixam_sdk/ai_bridge/text_based.py
mixam_sdk/item_specification/__init__.py
mixam_sdk/item_specification/enums/__init__.py
mixam_sdk/item_specification/enums/binding_colour.py
mixam_sdk/item_specification/enums/binding_edge.py
mixam_sdk/item_specification/enums/binding_loops.py
mixam_sdk/item_specification/enums/binding_type.py
mixam_sdk/item_specification/enums/border_type.py
mixam_sdk/item_specification/enums/colours.py
mixam_sdk/item_specification/enums/component_type.py
mixam_sdk/item_specification/enums/cover_area.py
mixam_sdk/item_specification/enums/end_paper_colour.py
mixam_sdk/item_specification/enums/flap_width.py
mixam_sdk/item_specification/enums/foiling_colour.py
mixam_sdk/item_specification/enums/frame_depth.py
mixam_sdk/item_specification/enums/head_and_tail_bands.py
mixam_sdk/item_specification/enums/lamination.py
mixam_sdk/item_specification/enums/orientation.py
mixam_sdk/item_specification/enums/pre_drilled_holes.py
mixam_sdk/item_specification/enums/product.py
mixam_sdk/item_specification/enums/ribbon_colour.py
mixam_sdk/item_specification/enums/sample_pack_type.py
mixam_sdk/item_specification/enums/shape.py
mixam_sdk/item_specification/enums/sheet_size.py
mixam_sdk/item_specification/enums/simple_fold.py
mixam_sdk/item_specification/enums/standard_size.py
mixam_sdk/item_specification/enums/substrate_colour.py
mixam_sdk/item_specification/enums/substrate_design.py
mixam_sdk/item_specification/enums/substrate_group.py
mixam_sdk/item_specification/enums/substrate_type.py
mixam_sdk/item_specification/enums/substrate_weights.py
mixam_sdk/item_specification/enums/unit_format.py
mixam_sdk/item_specification/interfaces/__init__.py
mixam_sdk/item_specification/interfaces/component_protocol.py
mixam_sdk/item_specification/interfaces/substrate_weight_protocol.py
mixam_sdk/item_specification/models/__init__.py
mixam_sdk/item_specification/models/binding.py
mixam_sdk-0.1.44.dist-info/METADATA
mixam_sdk-0.1.44.dist-info/WHEEL
mixam_sdk-0.1.44.dist-info/RECORD
