Metadata-Version: 2.4
Name: mixam-sdk
Version: 0.1.44
Summary: Mixam Python SDK: ItemSpecification Core Models & Enums. KeyBuilder & KeyParser For Working With Universal Keys
Keywords: mixam,sdk,printing
Author: Mixam
Author-email: developer@mixam.com
Requires-Python: >=3.12,<4.0
Classifier: Programming Language :: Python :: 3
Classifier: Programming Language :: Python :: 3.12
Classifier: Programming Language :: Python :: 3.13
Classifier: Programming Language :: Python :: 3.14
Requires-Dist: orjson (>=3.11.3,<4.0.0)
Requires-Dist: pydantic (>=2.11.7,<3.0.0)
Requires-Dist: pytest (>=8.4.1,<9.0.0)
Project-URL: Homepage, https://github.com/mixam-platform
Project-URL: Repository, https://github.com/mixam-platform/mixam-python-sdk
